zrjzrj/__init__.py
zrjzrj/main.py
zrjzrj-1.0.0.dist-info/LICENSE.txt
zrjzrj-1.0.0.dist-info/METADATA
zrjzrj-1.0.0.dist-info/WHEEL
zrjzrj-1.0.0.dist-info/entry_points.txt
zrjzrj-1.0.0.dist-info/top_level.txt
zrjzrj-1.0.0.dist-info/RECORD
